pplmyapi/__init__.py
pplmyapi/conf.py
pplmyapi/ppl.py
pplmyapi/validators.py
pplmyapi/connector/__init__.py
pplmyapi/connector/rest_connector.py
pplmyapi/connector/soap_connector.py
pplmyapi/connector/rest_actions/__init__.py
pplmyapi/connector/rest_actions/base.py
pplmyapi/connector/rest_actions/get_labels.py
pplmyapi/connector/rest_actions/shipment_batch.py
pplmyapi/connector/rest_actions/shipment_cancel.py
pplmyapi/connector/rest_actions/shipment_info.py
pplmyapi/connector/soap_actions/__init__.py
pplmyapi/connector/soap_actions/base.py
pplmyapi/models/__init__.py
pplmyapi/models/base.py
pplmyapi/models/dormant.py
pplmyapi/models/insurance.py
pplmyapi/models/package.py
pplmyapi/models/package_external_number.py
pplmyapi/models/package_flag.py
pplmyapi/models/package_service.py
pplmyapi/models/package_set.py
pplmyapi/models/payment_info.py
pplmyapi/models/recipient.py
pplmyapi/models/sender.py
pplmyapi/models/special_delivery.py
pplmyapi/models/weighted_package_info.py
pplmyapi-0.0.7.dist-info/LICENCE
pplmyapi-0.0.7.dist-info/METADATA
pplmyapi-0.0.7.dist-info/WHEEL
pplmyapi-0.0.7.dist-info/top_level.txt
pplmyapi-0.0.7.dist-info/RECORD
