Metadata-Version: 2.1
Name: pplmyapi
Version: 0.0.7
Summary: Python client for PPL myAPI
Home-page: https://github.com/michalpulpan/pplmyapi
Author: Michal Půlpán
Author-email: michal@michalpulpan.cz
License: MIT
Classifier: Programming Language :: Python :: 3.9
Classifier: Topic :: Utilities
Requires-Python: >=3.6
License-File: LICENCE
Requires-Dist: backports.cached-property (==1.0.2)
Requires-Dist: binapy (==0.6.0)
Requires-Dist: certifi (==2022.12.7)
Requires-Dist: cffi (==1.15.1)
Requires-Dist: charset-normalizer (==2.1.1)
Requires-Dist: cryptography (==39.0.0)
Requires-Dist: furl (==2.1.3)
Requires-Dist: idna (==3.4)
Requires-Dist: jwskate (==0.3.0)
Requires-Dist: lxml (==4.9.2)
Requires-Dist: oauthlib (==3.2.2)
Requires-Dist: orderedmultidict (==1.0.1)
Requires-Dist: pycparser (==2.21)
Requires-Dist: python-dotenv (==0.21.0)
Requires-Dist: requests (>=2.9.0)
Requires-Dist: six (==1.16.0)
Requires-Dist: typing-extensions (==4.4.0)
Requires-Dist: urllib3 (==1.26.13)
Requires-Dist: xmltodict (==0.13.0)
